examples/__init__.py
examples/definition_geometric_programming.py
examples/mcgill_lecture_programmatic.py
examples/simple_system_dynamic.py
examples/simple_system_programmatic.py
examples/wing_design.py
nhatc/__init__.py
nhatc/models/__init__.py
nhatc/models/coordinator.py
nhatc/models/problems.py
nhatc/models/variables.py
nhatc/utils/__init__.py
nhatc/utils/file_loader.py
nhatc-0.1.3.dist-info/licenses/LICENSE
tests/__init__.py
tests/test_programmatic_problem.py
nhatc-0.1.3.dist-info/METADATA
nhatc-0.1.3.dist-info/WHEEL
nhatc-0.1.3.dist-info/top_level.txt
nhatc-0.1.3.dist-info/RECORD
