Metadata-Version: 2.4
Name: nhatc
Version: 0.1.3
Summary: Library for running non-hierarchical multi-disciplinary optimization
Home-page: https://github.com/johnmartins/nhatc
Author: Julian Martinsson Bonde
Author-email: johnmartins1992@gmail.com
License: MIT
Classifier: Programming Language :: Python :: 3
Classifier: Programming Language :: Python :: 3.12
Classifier: Operating System :: OS Independent
Classifier: License :: OSI Approved :: MIT License
License-File: LICENSE
Requires-Dist: numpy==2.3.*
Requires-Dist: scipy==1.16.*
Requires-Dist: cexprtk==0.4.*
Provides-Extra: dev
Requires-Dist: pytest==8.*; extra == "dev"
Requires-Dist: twine>=4.0.2; extra == "dev"
Dynamic: author
Dynamic: author-email
Dynamic: classifier
Dynamic: description
Dynamic: description-content-type
Dynamic: home-page
Dynamic: license
Dynamic: license-file
Dynamic: provides-extra
Dynamic: requires-dist
Dynamic: summary
